asreviewcontrib/statistics/__init__.py
asreviewcontrib/statistics/_version.py
asreviewcontrib/statistics/entrypoint.py
asreviewcontrib/statistics/statistics.py
asreview_statistics-0.4.dist-info/LICENSE
asreview_statistics-0.4.dist-info/METADATA
asreview_statistics-0.4.dist-info/WHEEL
asreview_statistics-0.4.dist-info/entry_points.txt
asreview_statistics-0.4.dist-info/top_level.txt
asreview_statistics-0.4.dist-info/RECORD
