Metadata-Version: 2.1
Name: asreview-statistics
Version: 0.4
Summary: Statistical tools for the ASReview project
Home-page: https://github.com/msdslab/ASReview-statistics
Author: Utrecht University
Author-email: asreview@uu.nl
License: UNKNOWN
Project-URL: Bug Reports, https://github.com/asreview/ASReview-statistics/issues
Project-URL: Source, https://github.com/asreview/ASReview-statistics
Keywords: asreview statistics
Platform: UNKNOWN
Classifier: Development Status :: 3 - Alpha
Classifier: License :: OSI Approved :: Apache Software License
Classifier: Programming Language :: Python :: 3.5
Classifier: Programming Language :: Python :: 3.6
Classifier: Programming Language :: Python :: 3.7
Requires-Dist: asreview (>=0.7)
